odoo10_addon_base_iso3166-10.0.1.0.0-py2.7-nspkg.pth
odoo/addons/base_iso3166/README.rst
odoo/addons/base_iso3166/__init__.py
odoo/addons/base_iso3166/__manifest__.py
odoo/addons/base_iso3166/models/__init__.py
odoo/addons/base_iso3166/models/res_country.py
odoo/addons/base_iso3166/static/description/icon.png
odoo/addons/base_iso3166/static/description/icon.svg
odoo/addons/base_iso3166/views/country_view.xml
odoo10_addon_base_iso3166-10.0.1.0.0.dist-info/DESCRIPTION.rst
odoo10_addon_base_iso3166-10.0.1.0.0.dist-info/METADATA
odoo10_addon_base_iso3166-10.0.1.0.0.dist-info/RECORD
odoo10_addon_base_iso3166-10.0.1.0.0.dist-info/WHEEL
odoo10_addon_base_iso3166-10.0.1.0.0.dist-info/metadata.json
odoo10_addon_base_iso3166-10.0.1.0.0.dist-info/namespace_packages.txt
odoo10_addon_base_iso3166-10.0.1.0.0.dist-info/top_level.txt
